labml_db/__init__.py
labml_db/index.py
labml_db/key.py
labml_db/model.py
labml_db/types.py
labml_db/driver/__init__.py
labml_db/driver/file.py
labml_db/driver/mongo.py
labml_db/driver/redis.py
labml_db/index_driver/__init__.py
labml_db/index_driver/file.py
labml_db/index_driver/mongo.py
labml_db/index_driver/redis.py
labml_db/serializer/__init__.py
labml_db/serializer/json.py
labml_db/serializer/pickle.py
labml_db/serializer/utils.py
labml_db/serializer/yaml.py
labml_db-0.0.15.dist-info/METADATA
labml_db-0.0.15.dist-info/WHEEL
labml_db-0.0.15.dist-info/top_level.txt
labml_db-0.0.15.dist-info/RECORD
