Metadata-Version: 2.1
Name: labml-db
Version: 0.0.15
Summary: Minimalistic ORM for JSON/YAML/Pickle file based/redis/mongo DB
Home-page: https://github.com/labmlai/db
Author: Varuna Jayasiri, Nipun Wijerathne
Author-email: vpjayasiri@gmail.com, hnipun@gmail.com
License: UNKNOWN
Project-URL: Documentation, https://labml.ai
Keywords: database,json,yaml
Platform: UNKNOWN
Classifier: Programming Language :: Python :: 3
Classifier: License :: OSI Approved :: MIT License
Classifier: Intended Audience :: Developers
Classifier: Intended Audience :: Science/Research
Classifier: Topic :: Scientific/Engineering
Classifier: Topic :: Scientific/Engineering :: Mathematics
Classifier: Topic :: Scientific/Engineering :: Artificial Intelligence
Classifier: Topic :: Software Development
Classifier: Topic :: Software Development :: Libraries
Classifier: Topic :: Software Development :: Libraries :: Python Modules
Requires-Dist: pyyaml (>=5.3.1)
Requires-Dist: redis
